betterprints/__init__.py
betterprints/colors.py
betterprints/config.py
betterprints/configclass.py
betterprints/functions.py
betterprints/typeclasses.py
betterprints-0.1.3.dist-info/METADATA
betterprints-0.1.3.dist-info/WHEEL
betterprints-0.1.3.dist-info/top_level.txt
betterprints-0.1.3.dist-info/RECORD
