Metadata-Version: 2.1
Name: betterprints
Version: 0.1.3
Requires-Python: >=3.6
